vbinsta/__init__.py
vbinsta/__main__.py
vbinsta/choice_option.py
vbinsta/fetch.py
vbinsta/function_gpt.py
vbinsta/functions.py
vbinsta/login.py
vbinsta/main.py
vbinsta/render.py
vbinsta/token_cost_calculations.py
vbinsta/upload.py
vbinsta-0.1.16.dist-info/METADATA
vbinsta-0.1.16.dist-info/WHEEL
vbinsta-0.1.16.dist-info/entry_points.txt
vbinsta-0.1.16.dist-info/RECORD
