Metadata-Version: 2.1
Name: vbinsta
Version: 0.1.16
Summary: 
Author: vaibhavblayer
Author-email: vaibhavblayer@gmail.com
Requires-Python: >=3.12,<4.0
Classifier: Programming Language :: Python :: 3
Classifier: Programming Language :: Python :: 3.12
Requires-Dist: click (>=8.1.7,<9.0.0)
Requires-Dist: instagrapi (>=2.1.2,<3.0.0)
